<?xml version="1.0"?><Report><ReportQuery><Format><ReportTitle>Import Event</ReportTitle><ReportDescription></ReportDescription><PageSize>A4</PageSize><PageOrientation>Portrait</PageOrientation><TopMargin></TopMargin><BottomMargin></BottomMargin><RightMargin></RightMargin><LeftMargin></LeftMargin><pdfFont></pdfFont><pdfFontSize></pdfFontSize><PreExecuteCode>include(&quot;projects/ods/importevent.xml.php&quot;);</PreExecuteCode><bodyDisplay>show</bodyDisplay><graphDisplay>show</graphDisplay></Format><Datasource><SourceType>database</SourceType><SourceConnection><DatabaseType></DatabaseType><DatabaseName></DatabaseName><HostName>localhost</HostName><ServiceName></ServiceName><UserName></UserName><Password></Password></SourceConnection></Datasource><EntryForm><Query><TableSql>event_dimension</TableSql><WhereSql>                  </WhereSql><GroupSql></GroupSql><RowSelection>all</RowSelection><SQL><QuerySql></QuerySql><SQLLimitFirst></SQLLimitFirst><SQLSkipOffset></SQLSkipOffset></SQL><QueryColumns><QueryColumn><Name>event_id</Name><TableName></TableName><ColumnName>event_id</ColumnName><ColumnType>char</ColumnType><ColumnLength>30</ColumnLength><Format><column_display>show</column_display><content_type>plain</content_type><ColumnStartPDF></ColumnStartPDF><justify>left</justify><ColumnWidthPDF></ColumnWidthPDF><ColumnWidthHTML></ColumnWidthHTML><column_title></column_title><tooltip></tooltip><group_header_label></group_header_label><group_header_label_xpos></group_header_label_xpos><group_header_data_xpos></group_header_data_xpos><group_trailer_label></group_trailer_label></Format></QueryColumn><QueryColumn><Name>event_description</Name><TableName></TableName><ColumnName>event_description</ColumnName><ColumnType>char</ColumnType><ColumnLength>30</ColumnLength><Format><column_display>show</column_display><content_type>plain</content_type><ColumnStartPDF></ColumnStartPDF><justify>left</justify><ColumnWidthPDF></ColumnWidthPDF><ColumnWidthHTML></ColumnWidthHTML><column_title></column_title><tooltip></tooltip><group_header_label></group_header_label><group_header_label_xpos></group_header_label_xpos><group_header_data_xpos></group_header_data_xpos><group_trailer_label></group_trailer_label></Format></QueryColumn></QueryColumns><OrderColumns></OrderColumns><PreSQLS></PreSQLS></Query><Assignments></Assignments><Criteria></Criteria><Output><PageHeaders></PageHeaders><PageFooters></PageFooters><DisplayOrders><DisplayOrder><ColumnName>event_id</ColumnName><OrderNumber>1</OrderNumber></DisplayOrder><DisplayOrder><ColumnName>event_description</ColumnName><OrderNumber>2</OrderNumber></DisplayOrder></DisplayOrders><Groups></Groups><Graphs></Graphs></Output></EntryForm></ReportQuery></Report>